{
  "meta": {
    "title": "India vs Pakistan Cricket Final Broadcast",
    "description": "Millions of fans are streaming the live match, instant highlights, and post-match shows across TV apps and mobiles.",
    "price_caps_note": "Premium HD streams charge 1.45–1.95 credits, while quick highlight clips stay free to keep casual viewers happy.",
    "boost_logic": "Give extra capacity to the stadium cameras, Mumbai & Delhi control rooms, Lahore & Karachi viewing parties, and global fan zones (edges 0–7)."
  },
  "price_caps": [
    1.91,
    1.771,
    1.827,
    1.52,
    1.494,
    1.844,
    1.613,
    1.721,
    1.57,
    1.723,
    1.65,
    1.808,
    1.868,
    1.744,
    1.598,
    1.591,
    1.803,
    1.661,
    1.479,
    1.824,
    1.676,
    1.538,
    1.475,
    1.596,
    1.483,
    1.826,
    1.482,
    1.666,
    1.632,
    1.526,
    1.723,
    1.672
  ],
  "event_boosts": [
    [
      0.0,
      0.0,
      0.0,
      0.0,
      0.0,
      0.0,
      0.578,
      0.489,
      0.0,
      0.433,
      0.0,
      0.0,
      0.0,
      0.0,
      0.0,
      0.635
    ],
    [
      0.0,
      0.527,
      0.0,
      0.434,
      0.412,
      0.0,
      0.0,
      0.0,
      0.0,
      0.577,
      0.0,
      0.0,
      0.0,
      0.0,
      0.0,
      0.0
    ],
    [
      0.0,
      0.535,
      0.0,
      0.0,
      0.0,
      0.56,
      0.0,
      0.483,
      0.0,
      0.0,
      0.0,
      0.0,
      0.428,
      0.0,
      0.0,
      0.0
    ],
    [
      0.0,
      0.0,
      0.476,
      0.0,
      0.0,
      0.435,
      0.609,
      0.0,
      0.525,
      0.0,
      0.0,
      0.0,
      0.0,
      0.0,
      0.0,
      0.0
    ],
    [
      0.0,
      0.0,
      0.0,
      0.0,
      0.0,
      0.55,
      0.0,
      0.0,
      0.627,
      0.0,
      0.0,
      0.0,
      0.0,
      0.635,
      0.586,
      0.0
    ],
    [
      0.0,
      0.521,
      0.0,
      0.0,
      0.0,
      0.0,
      0.638,
      0.0,
      0.0,
      0.0,
      0.0,
      0.0,
      0.537,
      0.597,
      0.0,
      0.0
    ],
    [
      0.467,
      0.0,
      0.0,
      0.0,
      0.0,
      0.0,
      0.0,
      0.0,
      0.633,
      0.0,
      0.0,
      0.0,
      0.445,
      0.0,
      0.0,
      0.545
    ],
    [
      0.0,
      0.0,
      0.0,
      0.58,
      0.525,
      0.0,
      0.0,
      0.0,
      0.0,
      0.0,
      0.0,
      0.0,
      0.466,
      0.476,
      0.0,
      0.0
    ],
    [
      0.0,
      0.0,
      0.0,
      0.0,
      0.0,
      0.0,
      0.546,
      0.0,
      0.0,
      0.0,
      0.0,
      0.0,
      0.564,
      0.492,
      0.55,
      0.0
    ],
    [
      0.0,
      0.0,
      0.0,
      0.536,
      0.0,
      0.445,
      0.44,
      0.0,
      0.0,
      0.0,
      0.0,
      0.0,
      0.446,
      0.0,
      0.0,
      0.0
    ],
    [
      0.0,
      0.0,
      0.0,
      0.0,
      0.0,
      0.0,
      0.0,
      0.0,
      0.0,
      0.315,
      0.0,
      0.0,
      0.421,
      0.418,
      0.0,
      0.0
    ],
    [
      0.0,
      0.0,
      0.314,
      0.0,
      0.0,
      0.0,
      0.0,
      0.0,
      0.447,
      0.0,
      0.0,
      0.0,
      0.0,
      0.0,
      0.238,
      0.0
    ],
    [
      0.251,
      0.0,
      0.0,
      0.0,
      0.0,
      0.0,
      0.0,
      0.0,
      0.0,
      0.0,
      0.0,
      0.248,
      0.0,
      0.236,
      0.0,
      0.0
    ],
    [
      0.0,
      0.0,
      0.0,
      0.0,
      0.0,
      0.0,
      0.0,
      0.0,
      0.271,
      0.258,
      0.0,
      0.0,
      0.0,
      0.0,
      0.401,
      0.0
    ],
    [
      0.0,
      0.0,
      0.332,
      0.0,
      0.0,
      0.0,
      0.0,
      0.233,
      0.0,
      0.0,
      0.449,
      0.0,
      0.0,
      0.0,
      0.0,
      0.0
    ],
    [
      0.0,
      0.0,
      0.0,
      0.36,
      0.0,
      0.0,
      0.0,
      0.0,
      0.0,
      0.325,
      0.0,
      0.0,
      0.0,
      0.0,
      0.358,
      0.0
    ],
    [
      0.0,
      0.0,
      0.0,
      0.402,
      0.0,
      0.0,
      0.0,
      0.282,
      0.0,
      0.0,
      0.0,
      0.0,
      0.0,
      0.0,
      0.215,
      0.0
    ],
    [
      0.403,
      0.0,
      0.0,
      0.0,
      0.0,
      0.0,
      0.0,
      0.0,
      0.0,
      0.0,
      0.27,
      0.0,
      0.0,
      0.0,
      0.0,
      0.227
    ],
    [
      0.395,
      0.0,
      0.0,
      0.0,
      0.0,
      0.372,
      0.211,
      0.0,
      0.0,
      0.0,
      0.0,
      0.0,
      0.0,
      0.0,
      0.0,
      0.0
    ],
    [
      0.0,
      0.0,
      0.0,
      0.0,
      0.0,
      0.0,
      0.0,
      0.0,
      0.327,
      0.417,
      0.0,
      0.0,
      0.0,
      0.376,
      0.0,
      0.0
    ],
    [
      0.0,
      0.0,
      0.0,
      0.0,
      0.0,
      0.0,
      0.0,
      0.0,
      0.0,
      0.0,
      0.0,
      0.0,
      0.0,
      0.0,
      0.0,
      0.0
    ],
    [
      0.0,
      0.0,
      0.0,
      0.0,
      0.0,
      0.0,
      0.0,
      0.0,
      0.0,
      0.0,
      0.0,
      0.0,
      0.0,
      0.0,
      0.0,
      0.0
    ],
    [
      0.0,
      0.0,
      0.0,
      0.0,
      0.0,
      0.0,
      0.0,
      0.0,
      0.0,
      0.0,
      0.0,
      0.0,
      0.0,
      0.0,
      0.0,
      0.0
    ],
    [
      0.0,
      0.0,
      0.0,
      0.0,
      0.0,
      0.0,
      0.0,
      0.0,
      0.0,
      0.0,
      0.0,
      0.0,
      0.0,
      0.0,
      0.0,
      0.0
    ],
    [
      0.0,
      0.0,
      0.0,
      0.0,
      0.0,
      0.0,
      0.0,
      0.0,
      0.0,
      0.0,
      0.0,
      0.0,
      0.0,
      0.0,
      0.0,
      0.0
    ],
    [
      0.0,
      0.0,
      0.0,
      0.0,
      0.0,
      0.0,
      0.0,
      0.0,
      0.0,
      0.0,
      0.0,
      0.0,
      0.0,
      0.0,
      0.0,
      0.0
    ],
    [
      0.0,
      0.0,
      0.0,
      0.0,
      0.0,
      0.0,
      0.0,
      0.0,
      0.0,
      0.0,
      0.0,
      0.0,
      0.0,
      0.0,
      0.0,
      0.0
    ],
    [
      0.0,
      0.0,
      0.0,
      0.0,
      0.0,
      0.0,
      0.0,
      0.0,
      0.0,
      0.0,
      0.0,
      0.0,
      0.0,
      0.0,
      0.0,
      0.0
    ],
    [
      0.0,
      0.0,
      0.0,
      0.0,
      0.0,
      0.0,
      0.0,
      0.0,
      0.0,
      0.0,
      0.0,
      0.0,
      0.0,
      0.0,
      0.0,
      0.0
    ],
    [
      0.0,
      0.0,
      0.0,
      0.0,
      0.0,
      0.0,
      0.0,
      0.0,
      0.0,
      0.0,
      0.0,
      0.0,
      0.0,
      0.0,
      0.0,
      0.0
    ],
    [
      0.0,
      0.0,
      0.0,
      0.0,
      0.0,
      0.0,
      0.0,
      0.0,
      0.0,
      0.0,
      0.0,
      0.0,
      0.0,
      0.0,
      0.0,
      0.0
    ]
  ],
  "mu": [
    [
      210.178,
      208.997,
      99.911,
      82.577,
      121.422,
      144.86,
      125.63,
      113.796,
      210.712,
      84.36,
      181.175,
      113.555,
      204.673,
      177.904,
      187.714,
      219.772
    ],
    [
      178.101,
      138.048,
      182.248,
      122.149,
      133.108,
      191.789,
      127.325,
      215.569,
      146.468,
      212.61,
      192.652,
      133.7,
      210.476,
      219.135,
      165.72,
      133.544
    ],
    [
      205.727,
      201.43,
      219.128,
      117.813,
      146.556,
      118.242,
      141.324,
      170.808,
      158.02,
      213.447,
      162.508,
      122.712,
      128.581,
      127.125,
      165.567,
      87.809
    ],
    [
      172.635,
      201.646,
      164.926,
      177.358,
      163.486,
      142.542,
      92.41,
      112.442,
      89.736,
      161.211,
      133.887,
      153.119,
      120.271,
      138.925,
      195.852,
      134.098
    ],
    [
      139.184,
      217.174,
      103.578,
      184.598,
      113.811,
      132.615,
      167.81,
      169.171,
      84.18,
      184.194,
      161.623,
      154.72,
      126.746,
      215.877,
      107.646,
      109.467
    ],
    [
      218.237,
      169.739,
      200.373,
      196.135,
      178.244,
      204.62,
      118.606,
      87.941,
      137.342,
      216.084,
      146.171,
      117.16,
      161.551,
      146.566,
      170.825,
      190.57
    ],
    [
      123.479,
      168.845,
      92.215,
      111.626,
      166.525,
      151.288,
      140.795,
      87.506,
      130.091,
      178.349,
      204.643,
      96.335,
      208.136,
      197.147,
      107.614,
      144.922
    ],
    [
      163.828,
      125.662,
      152.726,
      84.106,
      103.76,
      152.727,
      181.128,
      127.306,
      137.686,
      136.492,
      167.703,
      126.815,
      203.7,
      87.251,
      172.802,
      101.532
    ],
    [
      131.346,
      89.979,
      84.808,
      201.235,
      174.762,
      167.15,
      101.834,
      119.903,
      118.663,
      165.24,
      124.052,
      185.485,
      174.276,
      191.081,
      95.906,
      134.922
    ],
    [
      151.423,
      106.586,
      145.451,
      147.906,
      186.375,
      214.459,
      85.015,
      200.906,
      162.941,
      149.337,
      186.876,
      218.748,
      93.4,
      99.28,
      122.937,
      140.491
    ],
    [
      120.702,
      213.018,
      175.159,
      119.944,
      188.503,
      120.222,
      165.091,
      159.583,
      102.347,
      187.973,
      131.755,
      218.524,
      179.746,
      107.556,
      129.315,
      107.443
    ],
    [
      141.899,
      181.399,
      151.649,
      119.023,
      203.007,
      177.25,
      122.664,
      113.643,
      194.244,
      169.984,
      189.499,
      206.783,
      130.274,
      174.551,
      142.701,
      82.261
    ],
    [
      207.635,
      110.595,
      101.148,
      218.418,
      125.071,
      167.029,
      208.96,
      198.472,
      218.419,
      148.887,
      116.245,
      109.003,
      217.715,
      99.753,
      188.248,
      120.598
    ],
    [
      185.059,
      219.175,
      160.875,
      148.891,
      211.841,
      189.048,
      186.816,
      164.886,
      129.383,
      129.99,
      199.31,
      130.128,
      160.746,
      85.946,
      98.469,
      96.48
    ],
    [
      123.996,
      130.779,
      137.939,
      182.179,
      170.386,
      174.171,
      114.487,
      181.836,
      110.405,
      188.167,
      195.135,
      129.027,
      106.878,
      171.241,
      106.577,
      183.62
    ],
    [
      212.057,
      190.937,
      171.355,
      81.278,
      96.507,
      186.856,
      160.987,
      165.841,
      95.899,
      82.148,
      204.464,
      211.721,
      88.669,
      170.789,
      113.739,
      192.87
    ],
    [
      136.266,
      125.507,
      181.168,
      190.709,
      199.295,
      209.342,
      128.528,
      135.288,
      186.284,
      180.135,
      210.824,
      219.224,
      85.878,
      94.995,
      188.673,
      202.849
    ],
    [
      92.086,
      160.788,
      139.275,
      160.018,
      215.21,
      174.362,
      218.561,
      120.258,
      197.748,
      117.37,
      156.92,
      120.852,
      97.267,
      105.647,
      118.322,
      140.324
    ],
    [
      95.914,
      211.578,
      141.44,
      174.625,
      187.091,
      134.349,
      96.169,
      173.374,
      166.618,
      105.464,
      208.774,
      113.775,
      214.414,
      162.831,
      165.689,
      209.98
    ],
    [
      198.672,
      152.605,
      198.347,
      139.918,
      169.59,
      110.786,
      201.406,
      96.322,
      85.255,
      153.82,
      155.952,
      121.445,
      184.076,
      164.109,
      105.323,
      114.017
    ],
    [
      142.846,
      173.874,
      143.162,
      164.377,
      116.986,
      190.289,
      184.282,
      175.953,
      191.932,
      180.261,
      196.506,
      178.048,
      95.816,
      164.524,
      84.419,
      80.219
    ],
    [
      181.63,
      212.876,
      113.681,
      175.08,
      107.538,
      203.133,
      145.859,
      121.177,
      175.382,
      108.371,
      86.271,
      98.89,
      98.661,
      193.756,
      186.944,
      96.874
    ],
    [
      200.658,
      92.976,
      81.142,
      166.569,
      92.647,
      199.9,
      141.281,
      200.744,
      103.234,
      142.276,
      182.234,
      214.876,
      114.13,
      124.309,
      126.589,
      80.494
    ],
    [
      184.806,
      189.112,
      117.721,
      162.675,
      91.048,
      94.281,
      81.349,
      183.873,
      192.363,
      160.57,
      191.078,
      147.195,
      216.523,
      154.293,
      186.386,
      131.055
    ],
    [
      191.418,
      185.532,
      87.668,
      169.968,
      89.534,
      110.928,
      129.54,
      206.918,
      166.701,
      198.734,
      131.823,
      206.441,
      88.602,
      149.863,
      87.43,
      80.937
    ],
    [
      190.77,
      98.01,
      149.551,
      186.095,
      101.339,
      131.21,
      199.265,
      162.93,
      124.586,
      215.521,
      131.742,
      106.962,
      169.224,
      199.267,
      117.763,
      192.609
    ],
    [
      215.284,
      137.785,
      218.025,
      109.68,
      160.84,
      211.521,
      132.816,
      169.144,
      108.376,
      91.14,
      114.793,
      198.259,
      159.895,
      191.541,
      184.547,
      168.695
    ],
    [
      214.2,
      134.454,
      138.264,
      127.844,
      183.365,
      117.493,
      196.834,
      188.026,
      91.649,
      148.062,
      82.396,
      164.126,
      126.723,
      125.719,
      124.539,
      209.351
    ],
    [
      149.054,
      105.183,
      166.749,
      207.684,
      217.677,
      144.35,
      92.54,
      203.068,
      179.796,
      162.69,
      100.014,
      145.04,
      183.718,
      195.863,
      124.097,
      157.769
    ],
    [
      212.502,
      156.262,
      167.26,
      215.672,
      193.282,
      197.376,
      110.804,
      167.172,
      165.974,
      87.65,
      94.38,
      131.452,
      154.21,
      183.113,
      102.174,
      170.684
    ],
    [
      209.537,
      115.642,
      169.332,
      80.87,
      216.653,
      147.616,
      156.614,
      164.338,
      95.938,
      94.08,
      85.796,
      170.745,
      141.168,
      134.075,
      88.72,
      94.485
    ],
    [
      180.494,
      195.4,
      141.475,
      92.525,
      116.104,
      167.116,
      80.322,
      95.982,
      179.795,
      157.414,
      118.784,
      202.182,
      100.187,
      211.063,
      185.829,
      163.357
    ]
  ],
  "sigma": [
    [
      19.978,
      11.115,
      17.155,
      13.334,
      11.017,
      14.328,
      19.704,
      16.319,
      19.291,
      10.67,
      12.985,
      19.609,
      13.184,
      6.41,
      11.002,
      16.025
    ],
    [
      15.988,
      14.799,
      5.613,
      15.877,
      5.587,
      10.189,
      5.382,
      6.285,
      9.581,
      19.185,
      6.015,
      12.054,
      19.539,
      7.168,
      10.428,
      7.824
    ],
    [
      17.29,
      15.658,
      15.732,
      17.416,
      18.975,
      12.551,
      18.804,
      15.203,
      6.568,
      11.108,
      18.826,
      7.071,
      9.866,
      7.003,
      14.379,
      19.223
    ],
    [
      8.947,
      13.14,
      15.78,
      6.209,
      16.924,
      16.523,
      14.177,
      5.636,
      12.042,
      15.399,
      13.946,
      19.45,
      11.385,
      7.526,
      19.212,
      17.085
    ],
    [
      12.475,
      16.954,
      16.345,
      12.071,
      19.703,
      15.815,
      5.504,
      7.501,
      12.413,
      7.158,
      16.345,
      17.843,
      14.032,
      15.03,
      13.572,
      13.931
    ],
    [
      13.891,
      18.992,
      5.293,
      17.679,
      7.753,
      10.568,
      6.393,
      11.229,
      7.542,
      5.624,
      6.73,
      8.381,
      12.087,
      11.638,
      14.127,
      18.236
    ],
    [
      19.372,
      8.39,
      12.088,
      6.896,
      16.155,
      11.292,
      13.017,
      11.116,
      11.635,
      8.289,
      15.117,
      16.011,
      15.927,
      12.441,
      13.044,
      18.961
    ],
    [
      8.793,
      5.764,
      16.718,
      14.077,
      13.917,
      8.17,
      9.21,
      11.314,
      17.647,
      16.504,
      10.937,
      16.091,
      14.381,
      17.301,
      10.187,
      15.148
    ],
    [
      6.861,
      18.496,
      5.211,
      18.735,
      12.689,
      11.558,
      16.453,
      5.803,
      13.362,
      8.946,
      10.087,
      11.398,
      11.065,
      11.954,
      9.588,
      18.251
    ],
    [
      5.885,
      5.161,
      18.477,
      8.147,
      12.673,
      17.635,
      7.933,
      18.728,
      8.17,
      9.149,
      17.33,
      18.164,
      5.496,
      5.404,
      19.975,
      7.978
    ],
    [
      16.751,
      9.587,
      11.429,
      14.942,
      13.877,
      11.478,
      9.653,
      10.102,
      11.907,
      8.961,
      19.183,
      7.312,
      18.508,
      15.855,
      18.562,
      8.542
    ],
    [
      17.099,
      5.189,
      9.603,
      5.242,
      18.697,
      9.385,
      19.478,
      17.31,
      9.196,
      14.169,
      12.047,
      12.982,
      12.968,
      5.418,
      14.799,
      16.02
    ],
    [
      15.187,
      18.721,
      6.761,
      14.304,
      18.838,
      13.102,
      7.396,
      16.115,
      12.613,
      14.549,
      8.092,
      13.13,
      5.587,
      18.176,
      5.396,
      7.878
    ],
    [
      15.014,
      5.517,
      17.332,
      16.805,
      10.745,
      16.105,
      5.63,
      12.995,
      17.052,
      16.507,
      5.694,
      10.635,
      16.085,
      8.024,
      19.145,
      6.765
    ],
    [
      9.816,
      7.597,
      10.984,
      8.187,
      17.097,
      6.324,
      11.37,
      15.803,
      11.804,
      12.071,
      7.317,
      17.036,
      6.248,
      12.503,
      12.326,
      12.972
    ],
    [
      14.684,
      11.954,
      6.046,
      16.863,
      12.303,
      6.018,
      11.603,
      8.932,
      8.384,
      18.516,
      5.427,
      10.982,
      11.257,
      8.822,
      15.688,
      8.34
    ],
    [
      17.797,
      7.12,
      13.435,
      9.021,
      6.244,
      16.551,
      15.083,
      17.701,
      11.313,
      16.595,
      13.018,
      7.593,
      16.278,
      5.569,
      11.008,
      8.346
    ],
    [
      14.271,
      7.303,
      17.789,
      8.257,
      13.41,
      16.07,
      11.428,
      14.141,
      16.971,
      11.56,
      8.445,
      15.352,
      7.244,
      16.011,
      13.333,
      7.741
    ],
    [
      5.409,
      8.964,
      10.925,
      17.131,
      17.961,
      19.904,
      7.295,
      15.419,
      17.5,
      5.169,
      7.803,
      18.562,
      13.536,
      13.797,
      5.792,
      8.123
    ],
    [
      6.639,
      17.73,
      5.388,
      13.758,
      15.561,
      13.974,
      5.949,
      8.402,
      13.399,
      9.168,
      10.376,
      6.593,
      10.048,
      11.643,
      17.195,
      10.449
    ],
    [
      17.457,
      10.632,
      5.888,
      8.606,
      19.366,
      18.674,
      9.062,
      12.742,
      15.362,
      15.497,
      5.603,
      19.775,
      10.822,
      5.811,
      19.083,
      6.719
    ],
    [
      11.792,
      7.678,
      19.692,
      8.543,
      11.43,
      8.398,
      20.0,
      13.979,
      14.555,
      19.835,
      5.407,
      18.411,
      14.952,
      17.697,
      15.025,
      19.003
    ],
    [
      7.28,
      5.985,
      9.527,
      16.866,
      9.405,
      19.861,
      17.457,
      10.088,
      10.327,
      19.16,
      7.454,
      19.86,
      6.263,
      14.625,
      11.635,
      16.12
    ],
    [
      15.793,
      8.491,
      12.226,
      10.861,
      5.048,
      5.908,
      7.858,
      7.855,
      9.79,
      9.07,
      11.71,
      7.958,
      11.843,
      8.174,
      13.338,
      5.498
    ],
    [
      14.786,
      19.391,
      17.515,
      6.425,
      17.156,
      10.148,
      14.379,
      7.71,
      14.245,
      16.276,
      8.322,
      18.87,
      9.253,
      15.709,
      13.592,
      14.336
    ],
    [
      17.22,
      15.768,
      6.113,
      19.482,
      18.279,
      5.86,
      15.25,
      16.425,
      5.432,
      16.205,
      18.621,
      9.148,
      9.665,
      11.433,
      12.702,
      12.001
    ],
    [
      11.754,
      10.924,
      6.082,
      11.788,
      5.49,
      6.234,
      11.874,
      17.682,
      9.752,
      10.667,
      5.251,
      8.215,
      17.943,
      6.887,
      6.837,
      16.266
    ],
    [
      13.468,
      8.613,
      15.423,
      15.669,
      9.65,
      5.126,
      11.019,
      5.266,
      9.518,
      18.286,
      9.781,
      15.489,
      5.458,
      5.252,
      11.488,
      10.57
    ],
    [
      7.677,
      18.961,
      9.479,
      5.998,
      8.606,
      17.358,
      15.165,
      12.354,
      6.885,
      13.093,
      17.717,
      11.224,
      8.684,
      7.236,
      6.003,
      18.079
    ],
    [
      9.119,
      10.342,
      16.592,
      15.679,
      12.626,
      18.297,
      12.265,
      12.22,
      6.284,
      16.907,
      7.266,
      18.559,
      5.375,
      11.179,
      11.091,
      9.495
    ],
    [
      17.843,
      12.603,
      15.257,
      6.105,
      5.062,
      19.504,
      16.876,
      16.727,
      14.683,
      8.336,
      7.715,
      17.655,
      10.302,
      7.626,
      16.447,
      18.307
    ],
    [
      14.006,
      5.271,
      6.346,
      8.66,
      13.961,
      10.568,
      6.52,
      6.496,
      15.007,
      5.235,
      15.199,
      17.742,
      14.135,
      11.017,
      18.732,
      13.236
    ]
  ]
}